tests/__init__.py
tests/test_grid.py
zenith/__init__.py
zenith/grid.py
zenith-0.0.4.dist-info/LICENSE
zenith-0.0.4.dist-info/METADATA
zenith-0.0.4.dist-info/WHEEL
zenith-0.0.4.dist-info/top_level.txt
zenith-0.0.4.dist-info/RECORD
